[
  {
    "id": 1,
    "name": "旺财",
    "type": "dog",
    "breed": "金毛寻回犬",
    "age": 18,
    "gender": "male",
    "size": "large",
    "vaccinated": true,
    "neutered": true,
    "description": "旺财是一只性格温顺的金毛，对人友善，喜欢和小朋友玩耍。已经完成基础训练，会坐下、握手等指令。",
    "health": "身体健康，已完成全套疫苗接种，定期驱虫。无遗传病史。",
    "personality": "温顺、活泼、亲人",
    "photoUrl": "https://picsum.photos/seed/pet1/400/300",
    "photos": [
      "https://picsum.photos/seed/pet1a/400/300",
      "https://picsum.photos/seed/pet1b/400/300"
    ],
    "status": "available",
    "createdAt": "2026-06-01T10:00:00Z"
  },
  {
    "id": 2,
    "name": "咪咪",
    "type": "cat",
    "breed": "英国短毛猫",
    "age": 12,
    "gender": "female",
    "size": "small",
    "vaccinated": true,
    "neutered": true,
    "description": "咪咪是一只可爱的英短蓝猫，圆脸大眼睛，性格安静，适合公寓饲养。",
    "health": "已绝育，完成疫苗接种，健康状况良好。",
    "personality": "安静、独立、爱干净",
    "photoUrl": "https://picsum.photos/seed/pet2/400/300",
    "photos": [
      "https://picsum.photos/seed/pet2a/400/300",
      "https://picsum.photos/seed/pet2b/400/300"
    ],
    "status": "available",
    "createdAt": "2026-06-05T10:00:00Z"
  },
  {
    "id": 3,
    "name": "豆豆",
    "type": "dog",
    "breed": "柯基",
    "age": 8,
    "gender": "male",
    "size": "small",
    "vaccinated": true,
    "neutered": false,
    "description": "豆豆是一只活泼好动的柯基犬，短腿大屁股，非常可爱。喜欢户外活动，精力充沛。",
    "health": "已完成基础疫苗，身体健康。需注意控制体重。",
    "personality": "活泼、好动、黏人",
    "photoUrl": "https://picsum.photos/seed/pet3/400/300",
    "photos": [
      "https://picsum.photos/seed/pet3a/400/300"
    ],
    "status": "available",
    "createdAt": "2026-06-10T10:00:00Z"
  },
  {
    "id": 4,
    "name": "小雪",
    "type": "cat",
    "breed": "暹罗猫",
    "age": 6,
    "gender": "female",
    "size": "small",
    "vaccinated": true,
    "neutered": false,
    "description": "小雪是一只漂亮的暹罗猫，蓝眼睛，话多爱撒娇。非常聪明，会自己开门。",
    "health": "已完成疫苗，无健康问题。",
    "personality": "聪明、粘人、爱叫",
    "photoUrl": "https://picsum.photos/seed/pet4/400/300",
    "photos": [
      "https://picsum.photos/seed/pet4a/400/300"
    ],
    "status": "available",
    "createdAt": "2026-06-12T10:00:00Z"
  },
  {
    "id": 5,
    "name": "大壮",
    "type": "dog",
    "breed": "哈士奇",
    "age": 24,
    "gender": "male",
    "size": "large",
    "vaccinated": true,
    "neutered": true,
    "description": "大壮是一只帅气的哈士奇，虽然有时候会犯二，但非常忠诚。需要有经验的领养人。",
    "health": "已完成疫苗和绝育，身体健康。",
    "personality": "活泼、犯二、忠诚",
    "photoUrl": "https://picsum.photos/seed/pet5/400/300",
    "photos": [
      "https://picsum.photos/seed/pet5a/400/300",
      "https://picsum.photos/seed/pet5b/400/300"
    ],
    "status": "available",
    "createdAt": "2026-06-15T10:00:00Z"
  },
  {
    "id": 6,
    "name": "球球",
    "type": "other",
    "breed": "荷兰垂耳兔",
    "age": 5,
    "gender": "female",
    "size": "small",
    "vaccinated": false,
    "neutered": false,
    "description": "球球是一只毛茸茸的垂耳兔，性格温顺，喜欢被人抚摸。适合有耐心的领养人。",
    "health": "健康活泼，定期体检。",
    "personality": "温顺、胆小、可爱",
    "photoUrl": "https://picsum.photos/seed/pet6/400/300",
    "photos": [
      "https://picsum.photos/seed/pet6a/400/300"
    ],
    "status": "available",
    "createdAt": "2026-06-18T10:00:00Z"
  },
  {
    "id": 7,
    "name": "花花",
    "type": "cat",
    "breed": "中华田园猫",
    "age": 15,
    "gender": "female",
    "size": "small",
    "vaccinated": true,
    "neutered": true,
    "description": "花花是一只三花猫，性格温柔，喜欢在窗边晒太阳。已经适应家庭生活。",
    "health": "已绝育和疫苗，非常健康。",
    "personality": "温柔、安静、独立",
    "photoUrl": "https://picsum.photos/seed/pet7/400/300",
    "photos": [
      "https://picsum.photos/seed/pet7a/400/300"
    ],
    "status": "available",
    "createdAt": "2026-06-20T10:00:00Z"
  },
  {
    "id": 8,
    "name": "小白",
    "type": "dog",
    "breed": "比熊",
    "age": 10,
    "gender": "male",
    "size": "small",
    "vaccinated": true,
    "neutered": true,
    "description": "小白是一只雪白的比熊犬，卷毛柔软，不掉毛。性格亲人，适合有小孩的家庭。",
    "health": "已完成绝育和疫苗，无泪痕问题。",
    "personality": "亲人、活泼、不掉毛",
    "photoUrl": "https://picsum.photos/seed/pet8/400/300",
    "photos": [
      "https://picsum.photos/seed/pet8a/400/300"
    ],
    "status": "pending",
    "createdAt": "2026-06-22T10:00:00Z"
  },
  {
    "id": 9,
    "name": "皮皮",
    "type": "dog",
    "breed": "泰迪",
    "age": 14,
    "gender": "male",
    "size": "small",
    "vaccinated": true,
    "neutered": true,
    "description": "皮皮是一只聪明的泰迪犬，会很多小把戏。非常粘人，喜欢和人待在一起。",
    "health": "健康，定期美容和体检。",
    "personality": "聪明、粘人、活泼",
    "photoUrl": "https://picsum.photos/seed/pet9/400/300",
    "photos": [
      "https://picsum.photos/seed/pet9a/400/300"
    ],
    "status": "available",
    "createdAt": "2026-06-25T10:00:00Z"
  },
  {
    "id": 10,
    "name": "小黑",
    "type": "cat",
    "breed": "孟买猫",
    "age": 9,
    "gender": "male",
    "size": "small",
    "vaccinated": true,
    "neutered": true,
    "description": "小黑是一只纯黑的孟买猫，绿眼睛，像小黑豹。性格温顺亲人。",
    "health": "已完成绝育和疫苗。",
    "personality": "温顺、亲人、安静",
    "photoUrl": "https://picsum.photos/seed/pet10/400/300",
    "photos": [
      "https://picsum.photos/seed/pet10a/400/300"
    ],
    "status": "available",
    "createdAt": "2026-06-28T10:00:00Z"
  },
  {
    "id": 11,
    "name": "元宝",
    "type": "other",
    "breed": "虎皮鹦鹉",
    "age": 4,
    "gender": "male",
    "size": "small",
    "vaccinated": false,
    "neutered": false,
    "description": "元宝是一只漂亮的虎皮鹦鹉，黄绿色羽毛，会学人说话。需要每天放风时间。",
    "health": "活泼健康，定期检查。",
    "personality": "活泼、聪明、会说话",
    "photoUrl": "https://picsum.photos/seed/pet11/400/300",
    "photos": [
      "https://picsum.photos/seed/pet11a/400/300"
    ],
    "status": "available",
    "createdAt": "2026-06-30T10:00:00Z"
  },
  {
    "id": 12,
    "name": "乐乐",
    "type": "dog",
    "breed": "拉布拉多",
    "age": 20,
    "gender": "female",
    "size": "large",
    "vaccinated": true,
    "neutered": true,
    "description": "乐乐是一只温柔的拉布拉多，性格稳定，非常适合作为家庭伴侣犬。已接受导盲犬基础训练。",
    "health": "已绝育，完成所有疫苗，髋关节健康。",
    "personality": "温柔、稳定、聪明",
    "photoUrl": "https://picsum.photos/seed/pet12/400/300",
    "photos": [
      "https://picsum.photos/seed/pet12a/400/300"
    ],
    "status": "available",
    "createdAt": "2026-07-01T10:00:00Z"
  },
  {
    "id": 13,
    "name": "橙子",
    "type": "cat",
    "breed": "橘猫",
    "age": 22,
    "gender": "male",
    "size": "medium",
    "vaccinated": true,
    "neutered": true,
    "description": "橙子是一只胖胖的橘猫，性格憨厚，最爱吃和睡。十橘九胖，它也不例外。",
    "health": "已绝育，需控制饮食，其他一切正常。",
    "personality": "贪吃、慵懒、憨厚",
    "photoUrl": "https://picsum.photos/seed/pet13/400/300",
    "photos": [
      "https://picsum.photos/seed/pet13a/400/300"
    ],
    "status": "available",
    "createdAt": "2026-07-02T10:00:00Z"
  },
  {
    "id": 14,
    "name": "布丁",
    "type": "dog",
    "breed": "博美",
    "age": 7,
    "gender": "female",
    "size": "small",
    "vaccinated": true,
    "neutered": false,
    "description": "布丁是一只毛茸茸的博美犬，小巧可爱，适合公寓饲养。虽然体型小但胆子大。",
    "health": "已完成疫苗，牙齿健康，无髌骨问题。",
    "personality": "勇敢、忠诚、警惕",
    "photoUrl": "https://picsum.photos/seed/pet14/400/300",
    "photos": [
      "https://picsum.photos/seed/pet14a/400/300"
    ],
    "status": "available",
    "createdAt": "2026-07-03T10:00:00Z"
  },
  {
    "id": 15,
    "name": "阿福",
    "type": "dog",
    "breed": "柴犬",
    "age": 16,
    "gender": "male",
    "size": "medium",
    "vaccinated": true,
    "neutered": true,
    "description": "阿福是一只表情丰富的柴犬，时而高冷时而粘人。非常爱干净，像猫一样。",
    "health": "已绝育和疫苗，身体健康。",
    "personality": "独立、爱干净、表情丰富",
    "photoUrl": "https://picsum.photos/seed/pet15/400/300",
    "photos": [
      "https://picsum.photos/seed/pet15a/400/300"
    ],
    "status": "available",
    "createdAt": "2026-07-05T10:00:00Z"
  }
]
